<?xml version="1.0" encoding="UTF-8"?>
<vcs-root xmlns:xsi="http://www.w3.org/2001/XMLSchema-instance" uuid="184f3e1f-8898-473a-baaa-3155c7f9ccab" type="jetbrains.git" xsi:noNamespaceSchemaLocation="http://www.jetbrains.com/teamcity/schemas/2017.2/project-config.xsd">
  <name>GithubDemo</name>
  <param name="agentCleanFilesPolicy" value="ALL_UNTRACKED" />
  <param name="agentCleanPolicy" value="ON_BRANCH_CHANGE" />
  <param name="authMethod" value="PASSWORD" />
  <param name="branch" value="refs/heads/master" />
  <param name="ignoreKnownHosts" value="true" />
  <param name="push_url" value="https://github.com/quigamdev/CIDemoApp.git" />
  <param name="secure:password" value="credentialsJSON:9a1b387e-e744-459b-8701-d4de0be6bb47" />
  <param name="submoduleCheckout" value="CHECKOUT" />
  <param name="teamcity:branchSpec" value="+:(*)" />
  <param name="url" value="https://github.com/quigamdev/CIDemoApp.git" />
  <param name="useAlternates" value="true" />
  <param name="username" value="sestakladislav.jr@gmail.com" />
  <param name="usernameStyle" value="USERID" />
</vcs-root>

